{
  "sales": [
    { "month": "Janeiro", "filterDate": "2024-01", "sales": 3030, "category": "A", "lat": "-30.0346", "lng": "-51.2177" },
    { "month": "Janeiro", "filterDate": "2024-01", "sales": 3000, "category": "B", "lat": "-30.0346", "lng": "-51.2177" },
    { "month": "Fevereiro", "filterDate": "2024-02", "sales": 1900, "category": "A", "lat": "-30.0450", "lng": "-51.2200" },
    { "month": "Fevereiro", "filterDate": "2024-02", "sales": 1700, "category": "B", "lat": "-30.0450", "lng": "-51.2200" },
    { "month": "Março", "filterDate": "2024-03", "sales": 2500, "category": "A", "lat": "-30.0470", "lng": "-51.2230" },
    { "month": "Março", "filterDate": "2024-03", "sales": 2900, "category": "B", "lat": "-30.0470", "lng": "-51.2230" },
    { "month": "Abril", "filterDate": "2024-04", "sales": 2500, "category": "A", "lat": "-30.0510", "lng": "-51.2150" },
    { "month": "Abril", "filterDate": "2024-04", "sales": 2800, "category": "B", "lat": "-30.0510", "lng": "-51.2150" },
    { "month": "Maio", "filterDate": "2024-05", "sales": 3000, "category": "A", "lat": "-30.0380", "lng": "-51.2100" },
    { "month": "Maio", "filterDate": "2024-05", "sales": 2000, "category": "B", "lat": "-30.0380", "lng": "-51.2100" },
    { "month": "Junho", "filterDate": "2024-06", "sales": 900, "category": "A", "lat": "-30.0400", "lng": "-51.2180" },
    { "month": "Junho", "filterDate": "2024-06", "sales": 1900, "category": "B", "lat": "-30.0400", "lng": "-51.2180" },
    { "month": "Julho", "filterDate": "2024-07", "sales": 0, "category": "A", "lat": "-30.0381456", "lng": "-51.231895" },
    { "month": "Julho", "filterDate": "2024-07", "sales": 7500, "category": "A", "lat": "-30.0381456", "lng": "-51.231895" },
    { "month": "Agosto", "filterDate": "2024-08", "sales": 4500, "category": "A", "lat": "-30.0420", "lng": "-51.2220" },
    { "month": "Agosto", "filterDate": "2024-08", "sales": 4000, "category": "B", "lat": "-30.0420", "lng": "-51.2220" },
    { "month": "Setembro", "filterDate": "2024-09", "sales": 1500, "category": "A", "lat": "-30.0480", "lng": "-51.2190" },
    { "month": "Setembro", "filterDate": "2024-09", "sales": 500, "category": "B", "lat": "-30.0480", "lng": "-51.2190" },
    { "month": "Outubro", "filterDate": "2024-10", "sales": 5500, "category": "B", "lat": "-30.0500", "lng": "-51.2210" },
    { "month": "Outubro", "filterDate": "2024-10", "sales": 0, "category": "B", "lat": "-30.0500", "lng": "-51.2210" },
    { "month": "Novembro", "filterDate": "2024-11", "sales": 6100, "category": "A", "lat": "-30.0390", "lng": "-51.2140" },
    { "month": "Novembro", "filterDate": "2024-11", "sales": 6800, "category": "B", "lat": "-30.0390", "lng": "-51.2140" },
    { "month": "Dezembro", "filterDate": "2024-12", "sales": 4500, "category": "A", "lat": "-30.0460", "lng": "-51.2130" },
    { "month": "Dezembro", "filterDate": "2024-12", "sales": 0, "category": "A", "lat": "-30.0460", "lng": "-51.2130" }
  ],
  "products": [
    { "name": "Produto 1", "filterDate": "2024-01", "sales": 3030, "category":"A" },
    { "name": "Produto 2", "filterDate": "2024-01", "sales": 3000, "category": "A" },
    { "name": "Produto 3", "filterDate": "2024-02", "sales": 1900, "category": "A" },
    { "name": "Produto 4", "filterDate": "2024-02", "sales": 1700, "category": "A" },
    { "name": "Produto 5", "filterDate": "2024-03", "sales": 2500, "category": "A" },
    { "name": "Produto 6", "filterDate": "2024-03", "sales": 2900, "category": "A" },
    { "name": "Produto 7", "filterDate": "2024-04", "sales": 2500, "category": "B" },
    { "name": "Produto 8", "filterDate": "2024-04", "sales": 2800, "category": "B" },
    { "name": "Produto 9", "filterDate": "2024-05", "sales": 3000, "category": "B" },
    { "name": "Produto 10", "filterDate": "2024-05", "sales": 2000, "category": "B" },
    { "name": "Produto 11", "filterDate": "2024-06", "sales": 900, "category": "B" },
    { "name": "Produto 12", "filterDate": "2024-06", "sales": 1900, "category": "B" },
    { "name": "Produto 13", "filterDate": "2024-07", "sales": 7500, "category":"A" },
    { "name": "Produto 14", "filterDate": "2024-07", "sales": 4500, "category": "A" },
    { "name": "Produto 15", "filterDate": "2024-08", "sales": 4000, "category": "A" },
    { "name": "Produto 16", "filterDate": "2024-08", "sales": 1500, "category": "A" },
    { "name": "Produto 17", "filterDate": "2024-09", "sales": 500, "category": "B" },
    { "name": "Produto 18", "filterDate": "2024-09", "sales": 5500, "category": "A" },
    { "name": "Produto 19", "filterDate": "2024-10", "sales": 6100, "category": "B" },
    { "name": "Produto 20", "filterDate": "2024-10", "sales": 6800, "category": "B" },
    { "name": "Produto 21", "filterDate": "2024-11", "sales": 6800, "category": "B" },
    { "name": "Produto 22", "filterDate": "2024-11", "sales": 6800, "category": "A" },
    { "name": "Produto 23", "filterDate": "2024-12", "sales": 6800, "category": "B" },
    { "name": "Produto 24", "filterDate": "2024-12", "sales": 4500, "category": "A" }
  ]
}